{"name":"Keydupl","tagline":"Duplicate the key into value an Object","body":"# keydupl [![Build Status](https://travis-ci.org/faizalpribadi/keydupl.svg?branch=master)](https://travis-ci.org/faizalpribadi/keydupl)\r\n\r\n> Duplicate the key into value an Object\r\n\r\n\r\n## Install\r\n\r\n```\r\n$ npm install --save keydupl\r\n```\r\n\r\n\r\n## Usage\r\n\r\n```js\r\nvar keydupl = require('keydupl');\r\n\r\nkeydupl(['a', 'b', 'c']);\r\n\r\n//=> { a: 'a', b: 'b', c: 'c' }\r\n```\r\n\r\n\r\n## API\r\n\r\n### keydupl([inputs])\r\n\r\n#### inputs\r\n\r\n*Required*\r\nType: `array`\r\n\r\nexample : `[\"a\", \"b\", \"c\"]`\r\n\r\n\r\n## License\r\n\r\nMIT © [faizalpribadi](http://faizalpribadi.github.io)\r\n","google":"","note":"Don't delete this file! It's used internally to help with page regeneration."}